{
  "ModelType": "Query",
  "Code": "cx_Applicants_More_Phones_SelectRows",
  "Name": "cx_Applicants_More_Phones_SelectRows",
  "ConnectionCode": "Default",
  "IsUsedForRightsFilter": false,
  "Columns": [
    {
      "Code": "Id",
      "Name": "Id",
      "Position": 1,
      "IsPrimaryKey": true,
      "ViewState": "Hidden",
      "IsPrintable": false
    },
    {
      "Code": "phone_type_name",
      "Name": "Тип",
      "Position": 2,
      "IsPrintable": false,
      "SqlName": "PhoneTypes.name",
      "FilterParameterCode": "@type"
    },
    {
      "Code": "phone_number",
      "Name": "Номер телефону",
      "Position": 3,
      "IsPrintable": false,
      "SqlName": "[ApplicantPhones].[phone_number]",
      "FilterParameterCode": "@phone"
    }
  ],
  "Parameters": [
    {
      "Code": "@pageOffsetRows",
      "Name": "pageOffsetRows",
      "ParameterType": "Integer",
      "IsPageOffsetRows": true
    },
    {
      "Code": "@pageLimitRows",
      "Name": "pageLimitRows",
      "ParameterType": "Integer",
      "IsPageLimitRows": true
    },
    {
      "Code": "@app_info",
      "Name": "app_info",
      "ParameterType": "Integer",
      "IsPrimaryKey": true
    }
  ]
}