{
  "css": "",
  "rootContainer": {
    "width": "auto",
    "margin": "0 5px 10px",
    "flexWrap": "wrap",
    "flexDirection": "row",
    "order": 1,
    "flexGrow": 1,
    "alignSelf": "auto",
    "border": "none",
    "children": [
      {
        "width": "auto",
        "margin": "0 5px 10px",
        "flexWrap": "wrap",
        "flexDirection": "row",
        "order": 1,
        "flexGrow": 1,
        "alignSelf": "flex-start",
        "border": "none",
        "children": [
          {
            "width": "auto",
            "margin": "0 5px 10px",
            "flexWrap": "wrap",
            "flexDirection": "column",
            "order": 1,
            "flexGrow": 1,
            "alignSelf": "flex-start",
            "border": "none",
            "children": [
              {
                "width": "auto",
                "margin": "0 5px 10px",
                "flexWrap": "wrap",
                "flexDirection": "row",
                "order": 1,
                "flexGrow": 1,
                "alignSelf": "auto",
                "border": "none",
                "children": [
                  {
                    "code": "tabs__CustomWidget",
                    "type": "CustomWidgetComponent",
                    "name": "tabs"
                  }
                ],
                "id": "Container-1",
                "height": "auto",
                "minHeight": "100px",
                "minWidth": "calc(100% - 10px)",
                "backgroundColor": "white"
              },
              {
                "width": "calc(100% - 10px)",
                "margin": "0 5px 10px",
                "flexWrap": "nowrap",
                "flexDirection": "row",
                "order": 1,
                "flexGrow": 1,
                "alignSelf": "auto",
                "border": "none",
                "children": [
                  {
                    "width": "calc(33% - 10px)",
                    "margin": "0 5px 10px",
                    "flexWrap": "wrap",
                    "flexDirection": "row",
                    "order": 1,
                    "flexGrow": 1,
                    "alignSelf": "auto",
                    "border": "none",
                    "children": [
                      {
                        "code": "1_1_speedDone_NativeDataGridWidget",
                        "type": "NativeDataGridWidgetComponent",
                        "name": "SpeedDone_1"
                      }
                    ],
                    "id": "Container-1",
                    "height": "calc(100% - 10px)",
                    "minHeight": "100px",
                    "minWidth": "100px",
                    "backgroundColor": "white",
                    "containerId": "1_1_speedDone"
                  },
                  {
                    "width": "calc(33% - 10px)",
                    "margin": "0 5px 10px",
                    "flexWrap": "wrap",
                    "flexDirection": "row",
                    "order": 1,
                    "flexGrow": 1,
                    "alignSelf": "auto",
                    "border": "none",
                    "children": [
                      {
                        "code": "1_2_speedDone_NativeDataGridWidget",
                        "type": "NativeDataGridWidgetComponent",
                        "name": "SpeedDone_2"
                      }
                    ],
                    "id": "Container-1",
                    "height": "calc(100% - 10px)",
                    "minHeight": "100px",
                    "minWidth": "100px",
                    "backgroundColor": "white",
                    "containerId": "1_2_speedDone"
                  },
                  {
                    "width": "calc(33% - 10px)",
                    "margin": "0 5px 10px",
                    "flexWrap": "wrap",
                    "flexDirection": "row",
                    "order": 1,
                    "flexGrow": 1,
                    "alignSelf": "auto",
                    "border": "none",
                    "children": [
                      {
                        "code": "1_3_speedDone_NativeDataGridWidget",
                        "type": "NativeDataGridWidgetComponent",
                        "name": "SpeedDone_3"
                      }
                    ],
                    "id": "Container-1",
                    "height": "calc(100% - 10px)",
                    "minHeight": "100px",
                    "minWidth": "100px",
                    "backgroundColor": "white",
                    "containerId": "1_3_speedDone"
                  }
                ],
                "id": "containerSpeedDone",
                "height": "calc(100% - 10px)",
                "minHeight": "100px",
                "minWidth": "100px",
                "backgroundColor": "white",
                "containerId": "containerSpeedDone"
              },
              {
                "width": "calc(100% - 10px)",
                "margin": "0 5px 10px",
                "flexWrap": "nowrap",
                "flexDirection": "row",
                "order": 1,
                "flexGrow": 1,
                "alignSelf": "auto",
                "border": "none",
                "children": [
                  {
                    "width": "calc(33% - 10px)",
                    "margin": "0 5px 10px",
                    "flexWrap": "wrap",
                    "flexDirection": "row",
                    "order": 1,
                    "flexGrow": 1,
                    "alignSelf": "auto",
                    "border": "none",
                    "children": [
                      {
                        "code": "2_1_speedExplained_NativeDataGridWidget",
                        "type": "NativeDataGridWidgetComponent",
                        "name": "SpeedExplained_1"
                      }
                    ],
                    "id": "Container-1",
                    "height": "calc(100% - 10px)",
                    "minHeight": "100px",
                    "minWidth": "100px",
                    "backgroundColor": "white",
                    "containerId": "2_1_speedExplained"
                  },
                  {
                    "width": "calc(33% - 10px)",
                    "margin": "0 5px 10px",
                    "flexWrap": "wrap",
                    "flexDirection": "row",
                    "order": 1,
                    "flexGrow": 1,
                    "alignSelf": "auto",
                    "border": "none",
                    "children": [
                      {
                        "code": "2_2_speedExplained_NativeDataGridWidget",
                        "type": "NativeDataGridWidgetComponent",
                        "name": "SpeedExplained_2"
                      }
                    ],
                    "id": "Container-1",
                    "height": "calc(100% - 10px)",
                    "minHeight": "100px",
                    "minWidth": "100px",
                    "backgroundColor": "white",
                    "containerId": "2_2_speedExplained"
                  },
                  {
                    "width": "calc(33% - 10px)",
                    "margin": "0 5px 10px",
                    "flexWrap": "wrap",
                    "flexDirection": "row",
                    "order": 1,
                    "flexGrow": 1,
                    "alignSelf": "auto",
                    "border": "none",
                    "children": [
                      {
                        "code": "2_3_speedExplained_NativeDataGridWidget",
                        "type": "NativeDataGridWidgetComponent",
                        "name": "SpeedExplained_3"
                      }
                    ],
                    "id": "Container-1",
                    "height": "calc(100% - 10px)",
                    "minHeight": "100px",
                    "minWidth": "100px",
                    "backgroundColor": "white",
                    "containerId": "2_3_speedExplained"
                  }
                ],
                "id": "containerSpeedExplained",
                "height": "calc(100% - 10px)",
                "minHeight": "100px",
                "minWidth": "100px",
                "backgroundColor": "white",
                "containerId": "containerSpeedExplained"
              },
              {
                "width": "calc(100% - 10px)",
                "margin": "0 5px 10px",
                "flexWrap": "nowrap",
                "flexDirection": "row",
                "order": 1,
                "flexGrow": 1,
                "alignSelf": "auto",
                "border": "none",
                "children": [
                  {
                    "width": "calc(33% - 10px)",
                    "margin": "0 5px 10px",
                    "flexWrap": "wrap",
                    "flexDirection": "row",
                    "order": 1,
                    "flexGrow": 1,
                    "alignSelf": "auto",
                    "border": "none",
                    "children": [
                      {
                        "code": "3_1_factDone_NativeDataGridWidget",
                        "type": "NativeDataGridWidgetComponent",
                        "name": "FactDone_1"
                      }
                    ],
                    "id": "Container-1",
                    "height": "calc(100% - 10px)",
                    "minHeight": "100px",
                    "minWidth": "100px",
                    "backgroundColor": "white",
                    "containerId": "3_1_factDone"
                  },
                  {
                    "width": "calc(33% - 10px)",
                    "margin": "0 5px 10px",
                    "flexWrap": "wrap",
                    "flexDirection": "row",
                    "order": 1,
                    "flexGrow": 1,
                    "alignSelf": "auto",
                    "border": "none",
                    "children": [
                      {
                        "code": "3_2_factDone_NativeDataGridWidget",
                        "type": "NativeDataGridWidgetComponent",
                        "name": "FactDone_2"
                      }
                    ],
                    "id": "Container-1",
                    "height": "calc(100% - 10px)",
                    "minHeight": "100px",
                    "minWidth": "100px",
                    "backgroundColor": "white",
                    "containerId": "3_2_factDone"
                  },
                  {
                    "width": "calc(33% - 10px)",
                    "margin": "0 5px 10px",
                    "flexWrap": "wrap",
                    "flexDirection": "row",
                    "order": 1,
                    "flexGrow": 1,
                    "alignSelf": "auto",
                    "border": "none",
                    "children": [
                      {
                        "code": "3_3_factDone_NativeDataGridWidget",
                        "type": "NativeDataGridWidgetComponent",
                        "name": "FactDone_3"
                      }
                    ],
                    "id": "Container-1",
                    "height": "calc(100% - 10px)",
                    "minHeight": "100px",
                    "minWidth": "100px",
                    "backgroundColor": "white",
                    "containerId": "3_3_factDone"
                  }
                ],
                "id": "containerFactDone",
                "height": "calc(100% - 10px)",
                "minHeight": "100px",
                "minWidth": "100px",
                "backgroundColor": "white",
                "containerId": "containerFactDone"
              }
            ],
            "id": "containersWrapper",
            "height": "auto",
            "minHeight": "100px",
            "minWidth": "100px",
            "backgroundColor": "white",
            "containerId": "containersWrapper"
          }
        ],
        "id": "Container-0",
        "height": "calc(100% - 10px)",
        "minHeight": "100px",
        "minWidth": "100px",
        "backgroundColor": "white"
      }
    ],
    "id": "Container-0",
    "height": "100%",
    "minHeight": "100%",
    "minWidth": "100%",
    "backgroundColor": "white"
  }
}